photorectify/__init__.py
photorectify/__main__.py
photorectify/exiftool.py
photorectify/lensfun-db.xml
photorectify-1.1.2.dist-info/entry_points.txt
photorectify-1.1.2.dist-info/LICENSE
photorectify-1.1.2.dist-info/WHEEL
photorectify-1.1.2.dist-info/METADATA
photorectify-1.1.2.dist-info/RECORD
