Metadata-Version: 2.1
Name: photorectify
Version: 1.1.2
Summary: Rectify lens distortions with Lensfun and OpenCV
Home-page: https://gitlab.com/archaeohelper/photorectify
Keywords: gis,image,lensfun,opencv,rectification
Author: David Berthel
Author-email: code@davidberthel.de
Requires-Python: >=3.7,<3.10
Classifier: Development Status :: 5 - Production/Stable
Classifier: Environment :: Console
Classifier: Intended Audience :: End Users/Desktop
Classifier: Intended Audience :: Science/Research
Classifier: License :: Other/Proprietary License
Classifier: Operating System :: OS Independent
Classifier: Programming Language :: Python :: 3
Classifier: Programming Language :: Python :: 3.7
Classifier: Programming Language :: Python :: 3.8
Classifier: Programming Language :: Python :: 3.9
Classifier: Topic :: Multimedia :: Graphics
Classifier: Topic :: Multimedia :: Graphics :: Capture :: Digital Camera
Classifier: Topic :: Multimedia :: Graphics :: Graphics Conversion
Classifier: Topic :: Scientific/Engineering :: GIS
Requires-Dist: Pillow (>=8.2.0,<9.0.0)
Requires-Dist: lensfunpy (>=1.8.0,<2.0.0)
Requires-Dist: numpy (>=1.20.2,<2.0.0)
Requires-Dist: opencv-contrib-python (>=4.5.1,<5.0.0)
Requires-Dist: pytest (>=6.2.4,<7.0.0)
Requires-Dist: scipy (>=1.6.2,<2.0.0)
Project-URL: Bug Tracker, https://github.com/python-poetry/poetry/issues
Project-URL: Repository, https://gitlab.com/archaeohelper/photorectify
